AUTHORS.md
LICENSE.md
LICENSE.txt
README.md
pyproject.toml
setup.cfg
setup.py
kensho_kenverters/__init__.py
kensho_kenverters/constants.py
kensho_kenverters/convert_output.py
kensho_kenverters/convert_output_visual_formatted.py
kensho_kenverters/extract_output_models.py
kensho_kenverters/output_to_sections.py
kensho_kenverters/output_to_tables.py
kensho_kenverters/table_to_text_objects.py
kensho_kenverters/tables_utils.py
kensho_kenverters/utils.py
kensho_kenverters.egg-info/PKG-INFO
kensho_kenverters.egg-info/SOURCES.txt
kensho_kenverters.egg-info/dependency_links.txt
kensho_kenverters.egg-info/requires.txt
kensho_kenverters.egg-info/top_level.txt