Metadata-Version: 2.4
Name: kensho_kenverters
Version: 1.3.0
Summary: Python Toolkit for Kensho Extract
Home-page: https://github.com/kensho-technologies/kenverters
Download-URL: https://github.com/kensho-technologies/kenverters/archive/refs/tags/v_1_2_9.tar.gz
Author: Valerie Faucon-Morin
Author-email: valerie.fauconmorin@spglobal.com
License: Apache-2.0
Keywords: Kensho Extract,Python Toolkit
Classifier: Development Status :: 3 - Alpha
Classifier: Intended Audience :: Developers
Classifier: Topic :: Software Development :: Build Tools
Classifier: License :: OSI Approved :: Apache Software License
Classifier: Programming Language :: Python :: 3.10
Classifier: Programming Language :: Python :: 3.11
License-File: LICENSE.md
License-File: LICENSE.txt
License-File: AUTHORS.md
Requires-Dist: pandas
Requires-Dist: pydantic
Dynamic: author
Dynamic: author-email
Dynamic: classifier
Dynamic: download-url
Dynamic: home-page
Dynamic: keywords
Dynamic: license
Dynamic: license-file
Dynamic: requires-dist
Dynamic: summary
